rtcpconnection/__init__.py
rtcpconnection/rtcpconnection.py
rtcpconnection-1.6.3.dist-info/METADATA
rtcpconnection-1.6.3.dist-info/WHEEL
rtcpconnection-1.6.3.dist-info/top_level.txt
rtcpconnection-1.6.3.dist-info/RECORD
